setup.cfg
setup.py
./collibra_luigi_client/__init__.py
./collibra_luigi_client/finale/__init__.py
./collibra_luigi_client/helper/__init__.py
./collibra_luigi_client/model/__init__.py
./collibra_luigi_client/model/community.py
./collibra_luigi_client/model/domain.py
./collibra_luigi_client/model/entry.py
./collibra_luigi_client/model/identifier.py
./collibra_luigi_client/model/type.py
./collibra_luigi_client/plot/__init__.py
./collibra_luigi_client/runner/__init__.py
./collibra_luigi_client/service/__init__.py
./collibra_luigi_client/service/beam.py
./collibra_luigi_client/service/collibra.py
./collibra_luigi_client/story/__init__.py
collibra_luigi_client.egg-info/PKG-INFO
collibra_luigi_client.egg-info/SOURCES.txt
collibra_luigi_client.egg-info/dependency_links.txt
collibra_luigi_client.egg-info/requires.txt
collibra_luigi_client.egg-info/top_level.txt