Metadata-Version: 2.1
Name: collibra-luigi-client
Version: 0.1.13
Summary: Collibra Luigi client with simple 3 tasks for importing assets
Home-page: 
Author: collibra
Author-email: antonio.castelo@collibra.com
License: MIT
Keywords: collibra,luigi
